ajallaan/__init__.py
ajallaan/__main__.py
ajallaan/api.py
ajallaan/cli.py
ajallaan/entry.py
ajallaan/epics.py
ajallaan/tree.py
ajallaan/workdays.py
ajallaan/worklog.py
ajallaan-2023.4.2.dist-info/LICENSE
ajallaan-2023.4.2.dist-info/METADATA
ajallaan-2023.4.2.dist-info/WHEEL
ajallaan-2023.4.2.dist-info/entry_points.txt
ajallaan-2023.4.2.dist-info/top_level.txt
ajallaan-2023.4.2.dist-info/RECORD
