Metadata-Version: 2.1
Name: ajallaan
Version: 2023.4.2
Summary: In due time (Finnish: ajallaan) - reporting on worklog entries of some ticket system.
Author-email: Stefan Hagen <stefan@hagen.link>
Maintainer-email: Stefan Hagen <stefan@hagen.link>
Project-URL: Homepage, https://git.sr.ht/~sthagen/ajallaan
Project-URL: Bug-Tracker, https://todo.sr.ht/~sthagen/ajallaan
Project-URL: Documentation, https://codes.dilettant.life/docs/ajallaan
Project-URL: Source-Code, https://git.sr.ht/~sthagen/ajallaan
Project-URL: Test-Coverage, https://codes.dilettant.life/coverage/ajallaan
Keywords: developer-tools,devops
Classifier: Development Status :: 3 - Alpha
Classifier: Intended Audience :: Developers
Classifier: License :: OSI Approved :: MIT License
Classifier: Programming Language :: Python :: 3.10
Classifier: Programming Language :: Python :: 3.11
Classifier: Programming Language :: Python :: 3.9
Requires-Python: >=3.9
License-File: LICENSE
Requires-Dist: attrs (>=22.2.0)
Requires-Dist: httpx (>=0.23.3)
Requires-Dist: msgspec (>=0.13.1)
Provides-Extra: dev
Requires-Dist: black ; extra == 'dev'
Requires-Dist: coverage ; extra == 'dev'
Requires-Dist: hypothesis ; extra == 'dev'
Requires-Dist: mypy ; extra == 'dev'
Requires-Dist: pytest ; extra == 'dev'
Requires-Dist: pytest-cov ; extra == 'dev'
Requires-Dist: pytest-flake8 ; extra == 'dev'
Requires-Dist: ruff ; extra == 'dev'
